pdmc
